clean.py
iclean-0.0.4.dist-info/LICENSE
iclean-0.0.4.dist-info/METADATA
iclean-0.0.4.dist-info/WHEEL
iclean-0.0.4.dist-info/entry_points.txt
iclean-0.0.4.dist-info/top_level.txt
iclean-0.0.4.dist-info/RECORD
