Metadata-Version: 2.1
Name: iclean
Version: 0.0.4
Summary: Unused imports cleaner
Author: kaliv0
License: GNU GENERAL PUBLIC LICENSE
Requires-Python: >=3.10
License-File: LICENSE
